COPYING.GPL
COPYING.TGPPL.rst
CREDITS
Dockerfile
MANIFEST.in
Makefile
NEWS.rst
README.rst
Tahoe.home
relnotes.txt
setup.cfg
setup.py
Contents/Info.plist
Contents/PkgInfo
Contents/MacOS/applet
Contents/Resources/applet.icns
Contents/Resources/applet.rsrc
Contents/Resources/Scripts/main.scpt
Contents/Resources/description.rtfd/TXT.rtf
bin/tahoe-script.template
docs/Makefile
docs/about.rst
docs/architecture.rst
docs/backdoors.rst
docs/backupdb.rst
docs/cautions.rst
docs/configuration.rst
docs/convergence-secret.rst
docs/debian.rst
docs/filesystem-notes.rst
docs/garbage-collection.rst
docs/helper.rst
docs/how_to_make_a_tahoe-lafs_release.org
docs/key-value-store.rst
docs/known_issues.rst
docs/lease-tradeoffs.svg
docs/logging.rst
docs/network-and-reliance-topology.svg
docs/nodekeys.rst
docs/performance.rst
docs/quickstart.rst
docs/running.rst
docs/stats.rst
docs/subtree1.svg
docs/write_coordination.rst
docs/build/build-pyOpenSSL.rst
docs/frontends/CLI.rst
docs/frontends/FTP-and-SFTP.rst
docs/frontends/download-status.rst
docs/frontends/drop-upload.rst
docs/frontends/webapi.rst
docs/historical/configuration.rst
docs/historical/historical_known_issues.txt
docs/historical/peer-selection-tahoe2.txt
docs/historical/peer-selection-tahoe3.txt
docs/historical/peer-selection.txt
docs/man/tahoe.1
docs/proposed/GridID.txt
docs/proposed/README.lossmodel
docs/proposed/accounting-overview.txt
docs/proposed/denver.txt
docs/proposed/leasedb.rst
docs/proposed/lossmodel.lyx
docs/proposed/mutable-DSA.svg
docs/proposed/mutable-DSA.txt
docs/proposed/mutsemi.svg
docs/proposed/old-accounts-introducer.txt
docs/proposed/old-accounts-pubkey.txt
docs/proposed/magic-folder/filesystem-integration.rst
docs/proposed/magic-folder/remote-to-local-sync.rst
docs/proposed/magic-folder/user-interface-design.rst
docs/specifications/CHK-hashes.svg
docs/specifications/Makefile
docs/specifications/URI-extension.rst
docs/specifications/dirnodes.rst
docs/specifications/file-encoding.rst
setuptools-0.6c16dev6.egg/EGG-INFO/PKG-INFO
setuptools-0.6c16dev6.egg/EGG-INFO/SOURCES.txt
setuptools-0.6c16dev6.egg/EGG-INFO/dependency_links.txt
setuptools-0.6c16dev6.egg/EGG-INFO/entry_points.txt
setuptools-0.6c16dev6.egg/EGG-INFO/top_level.txt
setuptools-0.6c16dev6.egg/EGG-INFO/zip-safe
src/allmydata_tahoe.egg-info/PKG-INFO
src/allmydata_tahoe.egg-info/SOURCES.txt
src/allmydata_tahoe.egg-info/dependency_links.txt
src/allmydata_tahoe.egg-info/entry_points.txt
src/allmydata_tahoe.egg-info/not-zip-safe
src/allmydata_tahoe.egg-info/requires.txt
src/allmydata_tahoe.egg-info/top_level.txt
